datafog/__about__.py
datafog/__init__.py
datafog/__init___lean.py
datafog/__init___original.py
datafog/client.py
datafog/config.py
datafog/core.py
datafog/exceptions.py
datafog/main.py
datafog/main_lean.py
datafog/main_original.py
datafog/models/__init__.py
datafog/models/annotator.py
datafog/models/anonymizer.py
datafog/models/common.py
datafog/models/spacy_nlp.py
datafog/processing/__init__.py
datafog/processing/image_processing/__init__.py
datafog/processing/image_processing/donut_processor.py
datafog/processing/image_processing/image_downloader.py
datafog/processing/image_processing/pytesseract_processor.py
datafog/processing/spark_processing/__init__.py
datafog/processing/spark_processing/pyspark_udfs.py
datafog/processing/text_processing/__init__.py
datafog/processing/text_processing/gliner_annotator.py
datafog/processing/text_processing/spacy_pii_annotator.py
datafog/processing/text_processing/regex_annotator/__init__.py
datafog/processing/text_processing/regex_annotator/regex_annotator.py
datafog/services/__init__.py
datafog/services/image_service.py
datafog/services/spark_service.py
datafog/services/text_service.py
datafog/services/text_service_lean.py
datafog/services/text_service_original.py
datafog-4.2.0.dist-info/licenses/LICENSE
datafog-4.2.0.dist-info/METADATA
datafog-4.2.0.dist-info/WHEEL
datafog-4.2.0.dist-info/entry_points.txt
datafog-4.2.0.dist-info/top_level.txt
datafog-4.2.0.dist-info/RECORD
