Metadata-Version: 2.4
Name: datafog
Version: 4.2.0
Summary: Lightning-fast PII detection and anonymization library with 190x performance advantage
Author: Sid Mohan
Author-email: sid@datafog.ai
Project-URL: Homepage, https://datafog.ai
Project-URL: Documentation, https://docs.datafog.ai
Project-URL: Discord, https://discord.gg/bzDth394R4
Project-URL: Twitter, https://twitter.com/datafoginc
Project-URL: GitHub, https://github.com/datafog/datafog-python
Keywords: pii detection anonymization privacy regex performance
Classifier: Development Status :: 4 - Beta
Classifier: Intended Audience :: Developers
Classifier: License :: OSI Approved :: Apache Software License
Classifier: Programming Language :: Python :: 3
Classifier: Programming Language :: Python :: 3.10
Classifier: Programming Language :: Python :: 3.11
Classifier: Programming Language :: Python :: 3.12
Classifier: Topic :: Software Development :: Libraries :: Python Modules
Classifier: Topic :: Text Processing
Classifier: Topic :: Security
Requires-Python: >=3.10,<3.13
License-File: LICENSE
Requires-Dist: pydantic<3.0,>=2.0
Requires-Dist: pydantic-settings>=2.0.0
Requires-Dist: typing-extensions>=4.0
Provides-Extra: nlp
Requires-Dist: spacy<4.0,>=3.7.0; extra == "nlp"
Provides-Extra: nlp-advanced
Requires-Dist: gliner>=0.2.5; extra == "nlp-advanced"
Requires-Dist: torch<2.7,>=2.1.0; extra == "nlp-advanced"
Requires-Dist: transformers>=4.20.0; extra == "nlp-advanced"
Requires-Dist: huggingface-hub>=0.16.0; extra == "nlp-advanced"
Provides-Extra: ocr
Requires-Dist: pytesseract>=0.3.0; extra == "ocr"
Requires-Dist: Pillow>=10.0.0; extra == "ocr"
Requires-Dist: sentencepiece>=0.2.0; extra == "ocr"
Requires-Dist: protobuf>=4.0.0; extra == "ocr"
Provides-Extra: distributed
Requires-Dist: pandas>=2.0.0; extra == "distributed"
Requires-Dist: numpy>=1.24.0; extra == "distributed"
Provides-Extra: web
Requires-Dist: fastapi>=0.100.0; extra == "web"
Requires-Dist: aiohttp>=3.8.0; extra == "web"
Requires-Dist: requests>=2.30.0; extra == "web"
Provides-Extra: cli
Requires-Dist: typer>=0.12.0; extra == "cli"
Requires-Dist: pydantic-settings>=2.0.0; extra == "cli"
Provides-Extra: crypto
Requires-Dist: cryptography>=40.0.0; extra == "crypto"
Provides-Extra: dev
Requires-Dist: pytest>=7.0.0; extra == "dev"
Requires-Dist: pytest-asyncio>=0.21.0; extra == "dev"
Requires-Dist: pytest-cov>=4.0.0; extra == "dev"
Requires-Dist: sphinx>=7.0.0; extra == "dev"
Provides-Extra: all
Requires-Dist: spacy<4.0,>=3.7.0; extra == "all"
Requires-Dist: gliner>=0.2.5; extra == "all"
Requires-Dist: torch<2.7,>=2.1.0; extra == "all"
Requires-Dist: transformers>=4.20.0; extra == "all"
Requires-Dist: huggingface-hub>=0.16.0; extra == "all"
Requires-Dist: pytesseract>=0.3.0; extra == "all"
Requires-Dist: Pillow>=10.0.0; extra == "all"
Requires-Dist: sentencepiece>=0.2.0; extra == "all"
Requires-Dist: protobuf>=4.0.0; extra == "all"
Requires-Dist: pandas>=2.0.0; extra == "all"
Requires-Dist: numpy>=1.24.0; extra == "all"
Requires-Dist: fastapi>=0.100.0; extra == "all"
Requires-Dist: aiohttp>=3.8.0; extra == "all"
Requires-Dist: requests>=2.30.0; extra == "all"
Requires-Dist: typer>=0.12.0; extra == "all"
Requires-Dist: pydantic-settings>=2.0.0; extra == "all"
Requires-Dist: cryptography>=40.0.0; extra == "all"
Dynamic: author
Dynamic: author-email
Dynamic: classifier
Dynamic: description
Dynamic: description-content-type
Dynamic: keywords
Dynamic: license-file
Dynamic: project-url
Dynamic: provides-extra
Dynamic: requires-dist
Dynamic: requires-python
Dynamic: summary
